{
  "cookies": [
    {
      "name": "session-username",
      "value": "standard_user",
      "domain": "www.saucedemo.com",
      "path": "/",
      "expires": 1774357674,
      "httpOnly": false,
      "secure": false,
      "sameSite": "Lax"
    }
  ],
  "origins": [
    {
      "origin": "https://www.saucedemo.com",
      "localStorage": [
        {
          "name": "backtrace-guid",
          "value": "a6fca8cd-0225-4181-b19b-586418fcc8fc"
        },
        {
          "name": "backtrace-last-active",
          "value": "1774357073914"
        }
      ]
    }
  ]
}